pywatson/__init__.py
pywatson/watson.py
pywatson/answer/__init__.py
pywatson/answer/answer.py
pywatson/answer/error_notification.py
pywatson/answer/evidence.py
pywatson/answer/evidence_profile.py
pywatson/answer/feature_group.py
pywatson/answer/passage.py
pywatson/answer/synonym.py
pywatson/answer/watson_answer.py
pywatson/question/__init__.py
pywatson/question/evidence_request.py
pywatson/question/filter.py
pywatson/question/watson_question.py
pywatson/util/__init__.py
pywatson/util/dictable.py
pywatson/util/map_initializable.py
pywatson-0.1.0a2.dist-info/DESCRIPTION.rst
pywatson-0.1.0a2.dist-info/METADATA
pywatson-0.1.0a2.dist-info/metadata.json
pywatson-0.1.0a2.dist-info/RECORD
pywatson-0.1.0a2.dist-info/top_level.txt
pywatson-0.1.0a2.dist-info/WHEEL
tests/answer/__init__.py
tests/answer/test_answer.py
tests/answer/__pycache__/__init__.cpython-34.pyc
tests/answer/__pycache__/test_answer.cpython-34-PYTEST.pyc
tests/answer/__pycache__/test_answer.cpython-34.pyc
tests/data/__init__.py
tests/data/answers.py
tests/data/questions.py
tests/data/__pycache__/__init__.cpython-34.pyc
tests/data/__pycache__/answers.cpython-34.pyc
tests/data/__pycache__/questions.cpython-34.pyc
tests/question/__init__.py
tests/question/test_question.py
tests/question/__pycache__/__init__.cpython-34.pyc
tests/question/__pycache__/test_question.cpython-34-PYTEST.pyc
tests/question/__pycache__/test_question.cpython-34.pyc
