Metadata-Version: 2.0
Name: pywatson
Version: 0.1.0a2
Summary: A Python adapter for IBM Watson's question and answer API
Home-page: https://github.com/sherlocke/pywatson
Author: Spencer Elliott
Author-email: me@elliottsj.com
License: MIT
Keywords: ibm watson
Platform: UNKNOWN
Classifier: Development Status :: 3 - Alpha
Classifier: Intended Audience :: Developers
Classifier: Topic :: Software Development :: Libraries :: Python Modules
Classifier: Topic :: Text Processing :: Linguistic
Classifier: License :: OSI Approved :: MIT License
Classifier: Programming Language :: Python :: 2.7
Classifier: Programming Language :: Python :: 3
Classifier: Programming Language :: Python :: 3.2
Classifier: Programming Language :: Python :: 3.3
Classifier: Programming Language :: Python :: 3.4
Requires-Dist: enum34
Requires-Dist: inflection
Requires-Dist: requests
Provides-Extra: dev
Requires-Dist: Sphinx; extra == 'dev'
Requires-Dist: sphinx-rtd-theme; extra == 'dev'
Provides-Extra: test
Requires-Dist: pytest; extra == 'test'
